spotify_backup_helper/__init__.py
spotify_backup_helper/main.py
spotify_backup_helper/prompts.py
spotify_backup_helper-2025.12.20185210.dist-info/METADATA
spotify_backup_helper-2025.12.20185210.dist-info/WHEEL
spotify_backup_helper-2025.12.20185210.dist-info/top_level.txt
spotify_backup_helper-2025.12.20185210.dist-info/RECORD
