Metadata-Version: 2.4
Name: spotify-backup-helper
Version: 2025.12.20185210
Summary: A new package that helps Spotify users securely back up their music library. By accepting simple text inputs that describe a user’s playlists, liked tracks, and saved albums, the tool generates a clea
Author-email: spotify-backup-helper <hi@eugene.plus>
License: MIT
Project-URL: Homepage, https://github.com/chigwell/spotify-backup-helper
Requires-Python: >=3.9
Requires-Dist: langchain-llm7>=0.0.0
Requires-Dist: llmatch-messages>=0.0.0
Requires-Dist: langchain-core>=0.3.0
